.gitignore
CITATION.cff
Example.ipynb
LICENSE
MANIFEST.in
README.md
cvplot.json
pyproject.toml
setup.cfg
setup.py
cvplot/__init__.py
cvplot/_version.py
cvplot/cvplot.py
cvplot/lime.py
cvplot/sensitivity_analysis.py
cvplot.egg-info/PKG-INFO
cvplot.egg-info/SOURCES.txt
cvplot.egg-info/dependency_links.txt
cvplot.egg-info/not-zip-safe
cvplot.egg-info/requires.txt
cvplot.egg-info/top_level.txt
cvplot/static/extension.js
cvplot/static/index.js
cvplot/static/index.js.map
js/README.md
js/package.json
js/webpack.config.js
js/yarn.lock
js/lib/App.vue
js/lib/cvplot.js
js/lib/d3-lasso.js
js/lib/embed.js
js/lib/extension.js
js/lib/index.js
js/lib/labplugin.js
js/lib/components/Contributions.vue
js/lib/components/Lineplot.vue
pip-wheel-metadata/cvplot.dist-info/METADATA
pip-wheel-metadata/cvplot.dist-info/top_level.txt